<artikel>
	<id>EKO_SA_07_592</id>
	<judul>Ekonom: LPS Lihat Kondisi Pasar Sebelum Turunkan Suku Bunga</judul>
	<tanggal>14/09/16</tanggal>
	<kata_kunci>ekonom, LPS, penurunan suku bunga LPS</kata_kunci>
	<isi>
		Ekonom Bank Permata Josua Pardede mengatakan, Lembaga Penjamin Simpanan (LPS) dipastikan telah mempertimbangkan kondisi pasar pada saat menentukan kenaikan atau penurunan suku bunga.

		"Berarti ini menunjukkan sebenarnya suku bunga deposito sudah turun," imbuhnya di Jakarta, Selasa (13/9/2016). (Baca: Suku Bunga Penjaminan LPS Turun 50 Basis Poin)

		Menurutnya, jika dilihat per Juli 2016, suku bunga deposito turun sekitar 91 basis  (bps) poin sejak dari awal tahun. Sementara, suku bunga acuan Bank Indonesia (BI rate) sudah turun 100 bps.

		Dia juga menilai, penurunan LPS rate mencermati atau merespons suku bunga di pasar. Di mana suku bunga deposito sudah turun meski suku bunga kreditnya masih belum turun.

		"Memang mestinya yang kita harapkan, suku bunga acuan dari BI (BI ate) direspons deposito perbankan dan kredit perbankan baru LPS rate. Memang jika ada penurunan di pasar atau perbankan, ya LPS rate layak diturunkan," tandasnya.	</isi>
	<link>http://ekbis.sindonews.com/read/1138993/178/ekonom-lps-lihat-kondisi-pasar-sebelum-turunkan-suku-bunga-1473771014</link>
</artikel>